{
    "tables":  {
                   "all":  [
                               {
                                   "logical_name":  "reseau_cloture___rec",
                                   "physical_name":  "cafil001_dat",
                                   "access_mode":  "READ",
                                   "id":  23,
                                   "usage_count":  1
                               },
                               {
                                   "logical_name":  "reseau_cloture___rec",
                                   "physical_name":  "cafil001_dat",
                                   "access_mode":  "WRITE",
                                   "id":  23,
                                   "usage_count":  2
                               },
                               {
                                   "logical_name":  "comptes_speciaux_spc",
                                   "physical_name":  "cafil004_dat",
                                   "access_mode":  "LINK",
                                   "id":  26,
                                   "usage_count":  1
                               },
                               {
                                   "logical_name":  "gm-recherche_____gmr",
                                   "physical_name":  "cafil008_dat",
                                   "access_mode":  "LINK",
                                   "id":  30,
                                   "usage_count":  1
                               },
                               {
                                   "logical_name":  "gm-recherche_____gmr",
                                   "physical_name":  "cafil008_dat",
                                   "access_mode":  "READ",
                                   "id":  30,
                                   "usage_count":  1
                               },
                               {
                                   "logical_name":  "hebergement______heb",
                                   "physical_name":  "cafil012_dat",
                                   "access_mode":  "LINK",
                                   "id":  34,
                                   "usage_count":  1
                               },
                               {
                                   "logical_name":  "depot_garantie___dga",
                                   "physical_name":  "cafil017_dat",
                                   "access_mode":  "READ",
                                   "id":  39,
                                   "usage_count":  1
                               },
                               {
                                   "logical_name":  "compte_gm________cgm",
                                   "physical_name":  "cafil025_dat",
                                   "access_mode":  "WRITE",
                                   "id":  47,
                                   "usage_count":  2
                               },
                               {
                                   "logical_name":  "tables___________tab",
                                   "physical_name":  "cafil045_dat",
                                   "access_mode":  "LINK",
                                   "id":  67,
                                   "usage_count":  1
                               },
                               {
                                   "logical_name":  "tables___________tab",
                                   "physical_name":  "cafil045_dat",
                                   "access_mode":  "READ",
                                   "id":  67,
                                   "usage_count":  2
                               },
                               {
                                   "logical_name":  "compteurs________cpt",
                                   "physical_name":  "cafil046_dat",
                                   "access_mode":  "WRITE",
                                   "id":  68,
                                   "usage_count":  1
                               },
                               {
                                   "logical_name":  "date_comptable___dat",
                                   "physical_name":  "cafil048_dat",
                                   "access_mode":  "LINK",
                                   "id":  70,
                                   "usage_count":  1
                               },
                               {
                                   "logical_name":  "articles_________art",
                                   "physical_name":  "cafil055_dat",
                                   "access_mode":  "LINK",
                                   "id":  77,
                                   "usage_count":  1
                               },
                               {
                                   "logical_name":  "articles_________art",
                                   "physical_name":  "cafil055_dat",
                                   "access_mode":  "READ",
                                   "id":  77,
                                   "usage_count":  2
                               },
                               {
                                   "logical_name":  "gratuites________gra",
                                   "physical_name":  "cafil057_dat",
                                   "access_mode":  "READ",
                                   "id":  79,
                                   "usage_count":  1
                               },
                               {
                                   "logical_name":  "moyen_paiement___mop",
                                   "physical_name":  "cafil067_dat",
                                   "access_mode":  "READ",
                                   "id":  89,
                                   "usage_count":  6
                               },
                               {
                                   "logical_name":  "logement_client__loc",
                                   "physical_name":  "cafil081_dat",
                                   "access_mode":  "LINK",
                                   "id":  103,
                                   "usage_count":  1
                               },
                               {
                                   "logical_name":  "table_utilisateurs",
                                   "physical_name":  "cafil087_dat",
                                   "access_mode":  "READ",
                                   "id":  109,
                                   "usage_count":  1
                               },
                               {
                                   "logical_name":  "fichier_validation",
                                   "physical_name":  "cafil109_dat",
                                   "access_mode":  "READ",
                                   "id":  131,
                                   "usage_count":  1
                               },
                               {
                                   "logical_name":  "articles_en_stock",
                                   "physical_name":  "caisse_artstock",
                                   "access_mode":  "LINK",
                                   "id":  197,
                                   "usage_count":  1
                               },
                               {
                                   "logical_name":  "cc_total_par_type",
                                   "physical_name":  "ccpartyp",
                                   "access_mode":  "READ",
                                   "id":  268,
                                   "usage_count":  1
                               },
                               {
                                   "logical_name":  "email",
                                   "physical_name":  "email",
                                   "access_mode":  "LINK",
                                   "id":  285,
                                   "usage_count":  1
                               },
                               {
                                   "logical_name":  "trf_transfert_new",
                                   "physical_name":  "transfertn",
                                   "access_mode":  "WRITE",
                                   "id":  461,
                                   "usage_count":  1
                               },
                               {
                                   "logical_name":  "saisie_od_taiforfait",
                                   "physical_name":  "%club_user%saisieod_dat",
                                   "access_mode":  "LINK",
                                   "id":  578,
                                   "usage_count":  3
                               },
                               {
                                   "logical_name":  "saisie_od_taiforfait",
                                   "physical_name":  "%club_user%saisieod_dat",
                                   "access_mode":  "WRITE",
                                   "id":  578,
                                   "usage_count":  3
                               },
                               {
                                   "logical_name":  "parametres_caisse",
                                   "physical_name":  "caisse_parametres",
                                   "access_mode":  "LINK",
                                   "id":  677,
                                   "usage_count":  1
                               },
                               {
                                   "logical_name":  "parametre_generaux",
                                   "physical_name":  "parametregen_dat",
                                   "access_mode":  "LINK",
                                   "id":  707,
                                   "usage_count":  1
                               },
                               {
                                   "logical_name":  "tpe_par_terminal old",
                                   "physical_name":  "termtpe_dat",
                                   "access_mode":  "LINK",
                                   "id":  715,
                                   "usage_count":  1
                               },
                               {
                                   "logical_name":  "trace_modif_package",
                                   "physical_name":  "trace_modif_package",
                                   "access_mode":  "LINK",
                                   "id":  764,
                                   "usage_count":  2
                               },
                               {
                                   "logical_name":  "type_prestation",
                                   "physical_name":  "type_prestation",
                                   "access_mode":  "LINK",
                                   "id":  802,
                                   "usage_count":  6
                               },
                               {
                                   "logical_name":  "type_prestation",
                                   "physical_name":  "type_prestation",
                                   "access_mode":  "WRITE",
                                   "id":  802,
                                   "usage_count":  1
                               },
                               {
                                   "logical_name":  "total_jour_forfait_ski",
                                   "physical_name":  "total_jour_forfait_ski",
                                   "access_mode":  "LINK",
                                   "id":  849,
                                   "usage_count":  1
                               },
                               {
                                   "logical_name":  "total_jour_forfait_ski",
                                   "physical_name":  "total_jour_forfait_ski",
                                   "access_mode":  "READ",
                                   "id":  849,
                                   "usage_count":  2
                               },
                               {
                                   "logical_name":  "total_jour_forfait_ski",
                                   "physical_name":  "total_jour_forfait_ski",
                                   "access_mode":  "WRITE",
                                   "id":  849,
                                   "usage_count":  6
                               }
                           ],
                   "by_access":  {
                                     "LINK":  [
                                                  {
                                                      "logical_name":  "comptes_speciaux_spc",
                                                      "physical_name":  "cafil004_dat",
                                                      "access_mode":  "LINK",
                                                      "id":  26,
                                                      "usage_count":  1
                                                  },
                                                  {
                                                      "logical_name":  "gm-recherche_____gmr",
                                                      "physical_name":  "cafil008_dat",
                                                      "access_mode":  "LINK",
                                                      "id":  30,
                                                      "usage_count":  1
                                                  },
                                                  {
                                                      "logical_name":  "hebergement______heb",
                                                      "physical_name":  "cafil012_dat",
                                                      "access_mode":  "LINK",
                                                      "id":  34,
                                                      "usage_count":  1
                                                  },
                                                  {
                                                      "logical_name":  "tables___________tab",
                                                      "physical_name":  "cafil045_dat",
                                                      "access_mode":  "LINK",
                                                      "id":  67,
                                                      "usage_count":  1
                                                  },
                                                  {
                                                      "logical_name":  "date_comptable___dat",
                                                      "physical_name":  "cafil048_dat",
                                                      "access_mode":  "LINK",
                                                      "id":  70,
                                                      "usage_count":  1
                                                  },
                                                  {
                                                      "logical_name":  "articles_________art",
                                                      "physical_name":  "cafil055_dat",
                                                      "access_mode":  "LINK",
                                                      "id":  77,
                                                      "usage_count":  1
                                                  },
                                                  {
                                                      "logical_name":  "logement_client__loc",
                                                      "physical_name":  "cafil081_dat",
                                                      "access_mode":  "LINK",
                                                      "id":  103,
                                                      "usage_count":  1
                                                  },
                                                  {
                                                      "logical_name":  "articles_en_stock",
                                                      "physical_name":  "caisse_artstock",
                                                      "access_mode":  "LINK",
                                                      "id":  197,
                                                      "usage_count":  1
                                                  },
                                                  {
                                                      "logical_name":  "email",
                                                      "physical_name":  "email",
                                                      "access_mode":  "LINK",
                                                      "id":  285,
                                                      "usage_count":  1
                                                  },
                                                  {
                                                      "logical_name":  "saisie_od_taiforfait",
                                                      "physical_name":  "%club_user%saisieod_dat",
                                                      "access_mode":  "LINK",
                                                      "id":  578,
                                                      "usage_count":  3
                                                  },
                                                  {
                                                      "logical_name":  "parametres_caisse",
                                                      "physical_name":  "caisse_parametres",
                                                      "access_mode":  "LINK",
                                                      "id":  677,
                                                      "usage_count":  1
                                                  },
                                                  {
                                                      "logical_name":  "parametre_generaux",
                                                      "physical_name":  "parametregen_dat",
                                                      "access_mode":  "LINK",
                                                      "id":  707,
                                                      "usage_count":  1
                                                  },
                                                  {
                                                      "logical_name":  "tpe_par_terminal old",
                                                      "physical_name":  "termtpe_dat",
                                                      "access_mode":  "LINK",
                                                      "id":  715,
                                                      "usage_count":  1
                                                  },
                                                  {
                                                      "logical_name":  "trace_modif_package",
                                                      "physical_name":  "trace_modif_package",
                                                      "access_mode":  "LINK",
                                                      "id":  764,
                                                      "usage_count":  2
                                                  },
                                                  {
                                                      "logical_name":  "type_prestation",
                                                      "physical_name":  "type_prestation",
                                                      "access_mode":  "LINK",
                                                      "id":  802,
                                                      "usage_count":  6
                                                  },
                                                  {
                                                      "logical_name":  "total_jour_forfait_ski",
                                                      "physical_name":  "total_jour_forfait_ski",
                                                      "access_mode":  "LINK",
                                                      "id":  849,
                                                      "usage_count":  1
                                                  }
                                              ],
                                     "READ":  [
                                                  {
                                                      "logical_name":  "reseau_cloture___rec",
                                                      "physical_name":  "cafil001_dat",
                                                      "access_mode":  "READ",
                                                      "id":  23,
                                                      "usage_count":  1
                                                  },
                                                  {
                                                      "logical_name":  "gm-recherche_____gmr",
                                                      "physical_name":  "cafil008_dat",
                                                      "access_mode":  "READ",
                                                      "id":  30,
                                                      "usage_count":  1
                                                  },
                                                  {
                                                      "logical_name":  "depot_garantie___dga",
                                                      "physical_name":  "cafil017_dat",
                                                      "access_mode":  "READ",
                                                      "id":  39,
                                                      "usage_count":  1
                                                  },
                                                  {
                                                      "logical_name":  "tables___________tab",
                                                      "physical_name":  "cafil045_dat",
                                                      "access_mode":  "READ",
                                                      "id":  67,
                                                      "usage_count":  2
                                                  },
                                                  {
                                                      "logical_name":  "articles_________art",
                                                      "physical_name":  "cafil055_dat",
                                                      "access_mode":  "READ",
                                                      "id":  77,
                                                      "usage_count":  2
                                                  },
                                                  {
                                                      "logical_name":  "gratuites________gra",
                                                      "physical_name":  "cafil057_dat",
                                                      "access_mode":  "READ",
                                                      "id":  79,
                                                      "usage_count":  1
                                                  },
                                                  {
                                                      "logical_name":  "moyen_paiement___mop",
                                                      "physical_name":  "cafil067_dat",
                                                      "access_mode":  "READ",
                                                      "id":  89,
                                                      "usage_count":  6
                                                  },
                                                  {
                                                      "logical_name":  "table_utilisateurs",
                                                      "physical_name":  "cafil087_dat",
                                                      "access_mode":  "READ",
                                                      "id":  109,
                                                      "usage_count":  1
                                                  },
                                                  {
                                                      "logical_name":  "fichier_validation",
                                                      "physical_name":  "cafil109_dat",
                                                      "access_mode":  "READ",
                                                      "id":  131,
                                                      "usage_count":  1
                                                  },
                                                  {
                                                      "logical_name":  "cc_total_par_type",
                                                      "physical_name":  "ccpartyp",
                                                      "access_mode":  "READ",
                                                      "id":  268,
                                                      "usage_count":  1
                                                  },
                                                  {
                                                      "logical_name":  "total_jour_forfait_ski",
                                                      "physical_name":  "total_jour_forfait_ski",
                                                      "access_mode":  "READ",
                                                      "id":  849,
                                                      "usage_count":  2
                                                  }
                                              ],
                                     "WRITE":  [
                                                   {
                                                       "logical_name":  "reseau_cloture___rec",
                                                       "physical_name":  "cafil001_dat",
                                                       "access_mode":  "WRITE",
                                                       "id":  23,
                                                       "usage_count":  2
                                                   },
                                                   {
                                                       "logical_name":  "compte_gm________cgm",
                                                       "physical_name":  "cafil025_dat",
                                                       "access_mode":  "WRITE",
                                                       "id":  47,
                                                       "usage_count":  2
                                                   },
                                                   {
                                                       "logical_name":  "compteurs________cpt",
                                                       "physical_name":  "cafil046_dat",
                                                       "access_mode":  "WRITE",
                                                       "id":  68,
                                                       "usage_count":  1
                                                   },
                                                   {
                                                       "logical_name":  "trf_transfert_new",
                                                       "physical_name":  "transfertn",
                                                       "access_mode":  "WRITE",
                                                       "id":  461,
                                                       "usage_count":  1
                                                   },
                                                   {
                                                       "logical_name":  "saisie_od_taiforfait",
                                                       "physical_name":  "%club_user%saisieod_dat",
                                                       "access_mode":  "WRITE",
                                                       "id":  578,
                                                       "usage_count":  3
                                                   },
                                                   {
                                                       "logical_name":  "type_prestation",
                                                       "physical_name":  "type_prestation",
                                                       "access_mode":  "WRITE",
                                                       "id":  802,
                                                       "usage_count":  1
                                                   },
                                                   {
                                                       "logical_name":  "total_jour_forfait_ski",
                                                       "physical_name":  "total_jour_forfait_ski",
                                                       "access_mode":  "WRITE",
                                                       "id":  849,
                                                       "usage_count":  6
                                                   }
                                               ]
                                 }
               },
    "orphan_analysis":  {
                            "has_public_name":  false,
                            "is_ecf_member":  false,
                            "has_callers":  false,
                            "status":  "ORPHELIN_POTENTIEL",
                            "reason":  "Aucun caller direct detecte - verifier PublicName et ECF"
                        },
    "statistics":  {
                       "callee_count":  6,
                       "expression_count":  110,
                       "logic_line_count":  1370,
                       "caller_count":  0,
                       "task_count":  39,
                       "disabled_line_count":  9,
                       "table_count":  26
                   },
    "call_graph":  {
                       "call_chain":  [

                                      ],
                       "callees":  [
                                       {
                                           "calls_count":  2,
                                           "name":  "Traitement des mails",
                                           "ide":  89
                                       },
                                       {
                                           "calls_count":  1,
                                           "name":  "Search client avec liste",
                                           "ide":  17
                                       },
                                       {
                                           "calls_count":  1,
                                           "name":  "Create logbook",
                                           "ide":  81
                                       },
                                       {
                                           "calls_count":  1,
                                           "name":  "Saisie Signature",
                                           "ide":  82
                                       },
                                       {
                                           "calls_count":  1,
                                           "name":  "Saisie Signature Validation",
                                           "ide":  83
                                       },
                                       {
                                           "calls_count":  1,
                                           "name":  "Zoom Mode paiement",
                                           "ide":  110
                                       }
                                   ],
                       "callers":  [

                                   ]
                   },
    "metadata":  {
                     "ide_position":  116,
                     "pipeline_version":  "7.1",
                     "project":  "WEL",
                     "program_name":  "Ventes *Sav au 02/07/2018",
                     "generated_at":  "2026-02-03 21:52:27"
                 }
}
