{
  "version": "1.0",
  "methodology": "SPECMAP",
  "created": "2026-02-11",
  "updated": "2026-02-23",
  "status": "verifying",
  "stats": {
    "total_programs": 350,
    "live_programs": 212,
    "orphan_programs": 138,
    "ecf_programs": 28,
    "contracted": 0,
    "enriched": 0,
    "verified": 18,
    "max_level": 8,
    "last_computed": "2026-02-20T01:47:08.991Z"
  },
  "batches": [
    {
      "id": "B1",
      "name": "Ouverture Session",
      "root": 122,
      "programs": 18,
      "status": "verified",
      "contracted_date": "2026-02-11",
      "verified_date": "2026-02-20",
      "stats": {
        "backend_na": 9,
        "frontend_enrich": 8,
        "fully_impl": 1,
        "coverage_avg_frontend": 49,
        "total_partial": 46,
        "total_missing": 101
      },
      "priority_order": [
        126,
        129,
        139,
        137,
        120,
        123,
        124,
        122
      ]
    },
    {
      "id": "B2",
      "name": "Caisse",
      "root": 281,
      "programs": 17,
      "status": "enriched",
      "enriched_date": "2026-02-22",
      "stats": {
        "backend_na": 0,
        "frontend_enrich": 0,
        "fully_impl": 12,
        "coverage_avg_frontend": 69,
        "total_partial": 0,
        "total_missing": 5
      },
      "priority_order": [
        281,
        121,
        116,
        119,
        125,
        131,
        132,
        134,
        155,
        156,
        117,
        118,
        128,
        133,
        142,
        138,
        47
      ],
      "domain": "Caisse",
      "complexity_grade": "D",
      "estimated_hours": 25.7,
      "auto_detected": true
    },
    {
      "id": "B3",
      "name": "General (1/2)",
      "root": 43,
      "programs": 25,
      "status": "enriched",
      "enriched_date": "2026-02-22",
      "stats": {
        "backend_na": 0,
        "frontend_enrich": 0,
        "fully_impl": 25,
        "coverage_avg_frontend": 65,
        "total_partial": 0,
        "total_missing": 0
      },
      "priority_order": [
        43,
        48,
        231,
        127,
        135,
        154,
        179,
        181,
        152,
        44,
        226,
        22,
        68,
        173,
        174,
        175,
        176,
        84,
        225,
        227,
        228,
        247,
        248,
        249,
        254
      ],
      "domain": "General",
      "complexity_grade": "D",
      "estimated_hours": 29.3,
      "auto_detected": true
    },
    {
      "id": "B4",
      "name": "General (2/2)",
      "root": 269,
      "programs": 23,
      "status": "pending",
      "stats": {
        "backend_na": 0,
        "frontend_enrich": 0,
        "fully_impl": 0,
        "coverage_avg_frontend": 0,
        "total_partial": 0,
        "total_missing": 0
      },
      "priority_order": [
        269,
        277,
        272,
        274,
        275,
        16,
        19,
        261,
        270,
        29,
        30,
        31,
        34,
        35,
        162,
        5,
        8,
        9,
        15,
        6,
        11,
        13,
        14
      ],
      "domain": "General",
      "complexity_grade": "D",
      "estimated_hours": 9.6,
      "auto_detected": true
    },
    {
      "id": "B5",
      "name": "Impression",
      "root": 151,
      "programs": 13,
      "status": "pending",
      "stats": {
        "backend_na": 0,
        "frontend_enrich": 0,
        "fully_impl": 0,
        "coverage_avg_frontend": 0,
        "total_partial": 0,
        "total_missing": 0
      },
      "priority_order": [
        151,
        136,
        182,
        180,
        183,
        150,
        185,
        208,
        296,
        17,
        171,
        251,
        10
      ],
      "domain": "Impression",
      "complexity_grade": "D",
      "estimated_hours": 17.1,
      "auto_detected": true
    },
    {
      "id": "B6",
      "name": "Compte",
      "root": 69,
      "programs": 8,
      "status": "pending",
      "stats": {
        "backend_na": 0,
        "frontend_enrich": 0,
        "fully_impl": 0,
        "coverage_avg_frontend": 0,
        "total_partial": 0,
        "total_missing": 0
      },
      "priority_order": [
        69,
        70,
        71,
        72,
        73,
        74,
        76,
        18
      ],
      "domain": "Compte",
      "complexity_grade": "D",
      "estimated_hours": 14.6,
      "auto_detected": true
    },
    {
      "id": "B7",
      "name": "Change",
      "root": 147,
      "programs": 10,
      "status": "pending",
      "stats": {
        "backend_na": 0,
        "frontend_enrich": 0,
        "fully_impl": 0,
        "coverage_avg_frontend": 0,
        "total_partial": 0,
        "total_missing": 0
      },
      "priority_order": [
        147,
        148,
        144,
        145,
        146,
        21,
        25,
        23,
        258,
        265
      ],
      "domain": "Change",
      "complexity_grade": "D",
      "estimated_hours": 10,
      "auto_detected": true
    },
    {
      "id": "B8",
      "name": "Stock",
      "root": 149,
      "programs": 3,
      "status": "pending",
      "stats": {
        "backend_na": 0,
        "frontend_enrich": 0,
        "fully_impl": 0,
        "coverage_avg_frontend": 0,
        "total_partial": 0,
        "total_missing": 0
      },
      "priority_order": [
        149,
        257,
        153
      ],
      "domain": "Stock",
      "complexity_grade": "D",
      "estimated_hours": 2,
      "auto_detected": true
    },
    {
      "id": "B9",
      "name": "Ventes",
      "root": 24,
      "programs": 16,
      "status": "pending",
      "stats": {
        "backend_na": 0,
        "frontend_enrich": 0,
        "fully_impl": 0,
        "coverage_avg_frontend": 0,
        "total_partial": 0,
        "total_missing": 0
      },
      "priority_order": [
        24,
        237,
        316,
        233,
        241,
        234,
        238,
        239,
        240,
        243,
        244,
        245,
        252,
        253,
        235,
        236
      ],
      "domain": "Ventes",
      "complexity_grade": "D",
      "estimated_hours": 24.9,
      "auto_detected": true
    },
    {
      "id": "B10",
      "name": "Divers",
      "root": 143,
      "programs": 8,
      "status": "pending",
      "stats": {
        "backend_na": 0,
        "frontend_enrich": 0,
        "fully_impl": 0,
        "coverage_avg_frontend": 0,
        "total_partial": 0,
        "total_missing": 0
      },
      "priority_order": [
        143,
        130,
        36,
        27,
        107,
        108,
        75,
        12
      ],
      "domain": "misc",
      "complexity_grade": "D",
      "estimated_hours": 9.7,
      "auto_detected": true
    },
    {
      "id": "B11",
      "name": "Comptes de depôt",
      "root": 40,
      "programs": 6,
      "status": "pending",
      "stats": {
        "backend_na": 0,
        "frontend_enrich": 0,
        "fully_impl": 0,
        "coverage_avg_frontend": 0,
        "total_partial": 0,
        "total_missing": 0
      },
      "priority_order": [
        40,
        39,
        172,
        262,
        263,
        266
      ],
      "domain": "",
      "complexity_grade": "D",
      "estimated_hours": 9,
      "auto_detected": true
    },
    {
      "id": "B12",
      "name": "Club Med Pass menu",
      "root": 77,
      "programs": 10,
      "status": "pending",
      "stats": {
        "backend_na": 0,
        "frontend_enrich": 0,
        "fully_impl": 0,
        "coverage_avg_frontend": 0,
        "total_partial": 0,
        "total_missing": 0
      },
      "priority_order": [
        77,
        78,
        79,
        80,
        81,
        82,
        86,
        184,
        186,
        87
      ],
      "domain": "",
      "complexity_grade": "D",
      "estimated_hours": 11.2,
      "auto_detected": true
    },
    {
      "id": "B13",
      "name": "Garantie sur compte",
      "root": 111,
      "programs": 8,
      "status": "pending",
      "stats": {
        "backend_na": 0,
        "frontend_enrich": 0,
        "fully_impl": 0,
        "coverage_avg_frontend": 0,
        "total_partial": 0,
        "total_missing": 0
      },
      "priority_order": [
        111,
        83,
        109,
        110,
        113,
        114,
        267,
        268
      ],
      "domain": "",
      "complexity_grade": "D",
      "estimated_hours": 10.3,
      "auto_detected": true
    },
    {
      "id": "B14",
      "name": "Fusion",
      "root": 28,
      "programs": 3,
      "status": "pending",
      "stats": {
        "backend_na": 0,
        "frontend_enrich": 0,
        "fully_impl": 0,
        "coverage_avg_frontend": 0,
        "total_partial": 0,
        "total_missing": 0
      },
      "priority_order": [
        28,
        32,
        33
      ],
      "domain": "",
      "complexity_grade": "D",
      "estimated_hours": 3.4,
      "auto_detected": true
    },
    {
      "id": "B15",
      "name": "Solde Easy Check Out",
      "root": 64,
      "programs": 15,
      "status": "pending",
      "stats": {
        "backend_na": 0,
        "frontend_enrich": 0,
        "fully_impl": 0,
        "coverage_avg_frontend": 0,
        "total_partial": 0,
        "total_missing": 0
      },
      "priority_order": [
        64,
        54,
        65,
        57,
        58,
        59,
        60,
        61,
        62,
        90,
        91,
        92,
        93,
        98,
        105
      ],
      "domain": "",
      "complexity_grade": "D",
      "estimated_hours": 9.6,
      "auto_detected": true
    },
    {
      "id": "B16",
      "name": "Factures (Tble Compta&Vent) V3",
      "root": 97,
      "programs": 6,
      "status": "pending",
      "stats": {
        "backend_na": 0,
        "frontend_enrich": 0,
        "fully_impl": 0,
        "coverage_avg_frontend": 0,
        "total_partial": 0,
        "total_missing": 0
      },
      "priority_order": [
        97,
        95,
        101,
        104,
        106,
        278
      ],
      "domain": "",
      "complexity_grade": "D",
      "estimated_hours": 4.4,
      "auto_detected": true
    },
    {
      "id": "B17",
      "name": "Start",
      "root": 166,
      "programs": 6,
      "status": "pending",
      "stats": {
        "backend_na": 0,
        "frontend_enrich": 0,
        "fully_impl": 0,
        "coverage_avg_frontend": 0,
        "total_partial": 0,
        "total_missing": 0
      },
      "priority_order": [
        166,
        45,
        52,
        200,
        224,
        223
      ],
      "domain": "",
      "complexity_grade": "D",
      "estimated_hours": 3.2,
      "auto_detected": true
    },
    {
      "id": "B18",
      "name": "Miscellaneous",
      "root": 20,
      "programs": 18,
      "status": "pending",
      "stats": {
        "backend_na": 0,
        "frontend_enrich": 0,
        "fully_impl": 0,
        "coverage_avg_frontend": 0,
        "total_partial": 0,
        "total_missing": 0
      },
      "priority_order": [
        20,
        42,
        51,
        53,
        112,
        164,
        165,
        167,
        168,
        169,
        170,
        178,
        192,
        210,
        221,
        229,
        232,
        256
      ],
      "domain": "misc",
      "complexity_grade": "D",
      "estimated_hours": 15.3,
      "auto_detected": true
    }
  ],
  "notes": [
    "Generated by /magic-live-subset command",
    "SPECMAP methodology: EXTRACT → MAP → GAP → CONTRACT → ENRICH → VERIFY",
    "B1 contracted: 18 programs, 8 frontend to enrich, avg coverage 49%"
  ],
  "migrate": {
    "47": {
      "status": "completed",
      "currentPhase": null,
      "phases": {
        "spec": {
          "status": "completed",
          "startedAt": "2026-02-23T14:43:45.066Z",
          "completedAt": "2026-02-23T14:43:45.073Z",
          "duration": 0,
          "file": "D:\\Projects\\Lecteur_Magic\\.openspec\\specs\\ADH-IDE-47.md"
        },
        "contract": {
          "status": "completed",
          "startedAt": "2026-02-23T14:43:45.074Z",
          "completedAt": "2026-02-23T14:43:45.075Z",
          "duration": 0,
          "file": "D:\\Projects\\Lecteur_Magic\\.openspec\\migration\\ADH\\ADH-IDE-47.contract.yaml"
        },
        "analyze": {
          "status": "completed",
          "startedAt": "2026-02-23T14:43:45.076Z",
          "completedAt": "2026-02-23T14:43:45.080Z",
          "duration": 0,
          "file": "D:\\Projects\\Lecteur_Magic\\.openspec\\migration\\ADH\\ADH-IDE-47.analysis.json"
        },
        "types": {
          "status": "completed",
          "startedAt": "2026-02-23T14:43:45.082Z",
          "completedAt": "2026-02-23T14:43:45.084Z",
          "duration": 0,
          "file": "D:\\Projects\\Lecteur_Magic\\adh-web\\src\\types\\sessionTimestamp.ts"
        },
        "store": {
          "status": "completed",
          "startedAt": "2026-02-23T14:43:45.086Z",
          "completedAt": "2026-02-23T14:43:45.087Z",
          "duration": 0,
          "file": "D:\\Projects\\Lecteur_Magic\\adh-web\\src\\stores\\sessionTimestampStore.ts"
        },
        "api": {
          "status": "completed",
          "startedAt": "2026-02-23T14:43:45.089Z",
          "completedAt": "2026-02-23T14:43:45.091Z",
          "duration": 0,
          "file": "D:\\Projects\\Lecteur_Magic\\adh-web\\src\\services\\api\\endpoints-sessionTimestamp.ts"
        },
        "page": {
          "status": "completed",
          "startedAt": "2026-02-23T14:43:45.093Z",
          "completedAt": "2026-02-23T14:43:45.098Z",
          "duration": 0,
          "file": "D:\\Projects\\Lecteur_Magic\\adh-web\\src\\pages\\SessionTimestampPage.tsx"
        },
        "components": {
          "status": "completed",
          "startedAt": "2026-02-23T14:43:45.099Z",
          "completedAt": "2026-02-23T14:43:45.104Z",
          "duration": 2
        },
        "tests-unit": {
          "status": "completed",
          "startedAt": "2026-02-23T14:43:45.106Z",
          "completedAt": "2026-02-23T14:43:45.108Z",
          "duration": 0,
          "file": "D:\\Projects\\Lecteur_Magic\\adh-web\\src\\__tests__\\sessionTimestampStore.test.ts"
        },
        "tests-ui": {
          "status": "completed",
          "startedAt": "2026-02-23T14:43:45.110Z",
          "completedAt": "2026-02-23T14:43:45.122Z",
          "duration": 0,
          "file": "D:\\Projects\\Lecteur_Magic\\adh-web\\src\\__tests__\\SessionTimestampPage.test.tsx"
        }
      },
      "files": [
        "D:\\Projects\\Lecteur_Magic\\.openspec\\specs\\ADH-IDE-47.md",
        "D:\\Projects\\Lecteur_Magic\\.openspec\\migration\\ADH\\ADH-IDE-47.contract.yaml",
        "D:\\Projects\\Lecteur_Magic\\.openspec\\migration\\ADH\\ADH-IDE-47.analysis.json",
        "D:\\Projects\\Lecteur_Magic\\adh-web\\src\\types\\sessionTimestamp.ts",
        "D:\\Projects\\Lecteur_Magic\\adh-web\\src\\stores\\sessionTimestampStore.ts",
        "D:\\Projects\\Lecteur_Magic\\adh-web\\src\\services\\api\\endpoints-sessionTimestamp.ts",
        "D:\\Projects\\Lecteur_Magic\\adh-web\\src\\pages\\SessionTimestampPage.tsx",
        "D:\\Projects\\Lecteur_Magic\\adh-web\\src\\__tests__\\sessionTimestampStore.test.ts",
        "D:\\Projects\\Lecteur_Magic\\adh-web\\src\\__tests__\\SessionTimestampPage.test.tsx"
      ],
      "errors": [],
      "startedAt": "2026-02-22T20:51:46.396Z",
      "completedAt": "2026-02-23T14:43:45.124Z"
    },
    "116": {
      "status": "pending",
      "currentPhase": null,
      "phases": {},
      "files": [
        "D:\\Projects\\Lecteur_Magic\\.openspec\\specs\\ADH-IDE-116.md",
        "D:\\Projects\\Lecteur_Magic\\.openspec\\migration\\ADH\\ADH-IDE-116.contract.yaml",
        "D:\\Projects\\Lecteur_Magic\\.openspec\\migration\\ADH\\ADH-IDE-116.analysis.json",
        "D:\\Projects\\Lecteur_Magic\\adh-web\\src\\types\\sessionConcurrency.ts",
        "D:\\Projects\\Lecteur_Magic\\adh-web\\src\\stores\\sessionConcurrencyStore.ts",
        "D:\\Projects\\Lecteur_Magic\\adh-web\\src\\services\\api\\endpoints-sessionConcurrency.ts",
        "D:\\Projects\\Lecteur_Magic\\adh-web\\src\\pages\\SessionConcurrencyPage.tsx",
        "D:\\Projects\\Lecteur_Magic\\adh-web\\src\\__tests__\\sessionConcurrencyStore.test.ts",
        "D:\\Projects\\Lecteur_Magic\\adh-web\\src\\__tests__\\SessionConcurrencyPage.test.tsx"
      ],
      "errors": [],
      "startedAt": "2026-02-22T21:43:30.599Z",
      "completedAt": "2026-02-22T21:43:30.643Z"
    },
    "117": {
      "status": "pending",
      "currentPhase": null,
      "phases": {},
      "files": [
        "D:\\Projects\\Lecteur_Magic\\.openspec\\specs\\ADH-IDE-117.md",
        "D:\\Projects\\Lecteur_Magic\\.openspec\\migration\\ADH\\ADH-IDE-117.contract.yaml",
        "D:\\Projects\\Lecteur_Magic\\.openspec\\migration\\ADH\\ADH-IDE-117.analysis.json",
        "D:\\Projects\\Lecteur_Magic\\adh-web\\src\\types\\sessionHistory.ts",
        "D:\\Projects\\Lecteur_Magic\\adh-web\\src\\stores\\sessionHistoryStore.ts",
        "D:\\Projects\\Lecteur_Magic\\adh-web\\src\\services\\api\\endpoints-sessionHistory.ts",
        "D:\\Projects\\Lecteur_Magic\\adh-web\\src\\pages\\SessionHistoryPage.tsx",
        "D:\\Projects\\Lecteur_Magic\\adh-web\\src\\__tests__\\sessionHistoryStore.test.ts",
        "D:\\Projects\\Lecteur_Magic\\adh-web\\src\\__tests__\\SessionHistoryPage.test.tsx"
      ],
      "errors": [],
      "startedAt": "2026-02-22T21:19:37.897Z",
      "completedAt": "2026-02-22T21:19:37.937Z"
    },
    "118": {
      "status": "generating",
      "currentPhase": "tests-unit",
      "phases": {
        "spec": {
          "status": "completed",
          "startedAt": "2026-02-23T16:35:32.857Z",
          "completedAt": "2026-02-23T16:35:32.862Z",
          "duration": 0,
          "file": "D:\\Projects\\Lecteur_Magic\\.openspec\\specs\\ADH-IDE-118.md"
        },
        "contract": {
          "status": "completed",
          "startedAt": "2026-02-23T16:35:32.862Z",
          "completedAt": "2026-02-23T16:35:32.862Z",
          "duration": 0,
          "file": "D:\\Projects\\Lecteur_Magic\\.openspec\\migration\\ADH\\ADH-IDE-118.contract.yaml"
        },
        "analyze": {
          "status": "completed",
          "startedAt": "2026-02-23T16:35:32.863Z",
          "completedAt": "2026-02-23T16:35:32.908Z",
          "duration": 0,
          "file": "D:\\Projects\\Lecteur_Magic\\.openspec\\migration\\ADH\\ADH-IDE-118.analysis.json"
        },
        "types": {
          "status": "completed",
          "startedAt": "2026-02-23T16:35:32.909Z",
          "completedAt": "2026-02-23T16:35:59.848Z",
          "duration": 26939,
          "file": "D:\\Projects\\Lecteur_Magic\\adh-web\\src\\types\\sessionsOuvertes.ts"
        },
        "store": {
          "status": "completed",
          "startedAt": "2026-02-23T16:35:59.849Z",
          "completedAt": "2026-02-23T16:36:35.847Z",
          "duration": 35998,
          "file": "D:\\Projects\\Lecteur_Magic\\adh-web\\src\\stores\\sessionsOuvertesStore.ts"
        },
        "api": {
          "status": "completed",
          "startedAt": "2026-02-23T16:36:35.848Z",
          "completedAt": "2026-02-23T16:36:57.389Z",
          "duration": 21541,
          "file": "D:\\Projects\\Lecteur_Magic\\adh-web\\src\\services\\api\\endpoints-sessionsOuvertes.ts"
        },
        "page": {
          "status": "completed",
          "startedAt": "2026-02-23T16:36:57.391Z",
          "completedAt": "2026-02-23T16:37:40.826Z",
          "duration": 43435,
          "file": "D:\\Projects\\Lecteur_Magic\\adh-web\\src\\pages\\SessionsOuvertesPage.tsx"
        },
        "components": {
          "status": "completed",
          "startedAt": "2026-02-23T16:37:40.827Z",
          "completedAt": "2026-02-23T16:38:08.874Z",
          "duration": 28047
        },
        "tests-unit": {
          "status": "completed",
          "startedAt": "2026-02-23T16:38:08.875Z",
          "completedAt": "2026-02-23T16:39:09.445Z",
          "duration": 60570,
          "file": "D:\\Projects\\Lecteur_Magic\\adh-web\\src\\__tests__\\sessionsOuvertesStore.test.ts"
        }
      },
      "files": [
        "D:\\Projects\\Lecteur_Magic\\.openspec\\specs\\ADH-IDE-118.md",
        "D:\\Projects\\Lecteur_Magic\\.openspec\\migration\\ADH\\ADH-IDE-118.contract.yaml",
        "D:\\Projects\\Lecteur_Magic\\.openspec\\migration\\ADH\\ADH-IDE-118.analysis.json",
        "D:\\Projects\\Lecteur_Magic\\adh-web\\src\\types\\sessionsOuvertes.ts",
        "D:\\Projects\\Lecteur_Magic\\adh-web\\src\\stores\\sessionsOuvertesStore.ts",
        "D:\\Projects\\Lecteur_Magic\\adh-web\\src\\services\\api\\endpoints-sessionsOuvertes.ts",
        "D:\\Projects\\Lecteur_Magic\\adh-web\\src\\pages\\SessionsOuvertesPage.tsx",
        "D:\\Projects\\Lecteur_Magic\\adh-web\\src\\__tests__\\sessionsOuvertesStore.test.ts",
        "D:\\Projects\\Lecteur_Magic\\adh-web\\src\\__tests__\\SessionsOuvertesPage.test.tsx"
      ],
      "errors": [],
      "startedAt": "2026-02-22T20:51:46.356Z",
      "completedAt": "2026-02-23T14:43:45.017Z"
    },
    "119": {
      "status": "pending",
      "currentPhase": null,
      "phases": {},
      "files": [
        "D:\\Projects\\Lecteur_Magic\\.openspec\\specs\\ADH-IDE-119.md",
        "D:\\Projects\\Lecteur_Magic\\.openspec\\migration\\ADH\\ADH-IDE-119.contract.yaml",
        "D:\\Projects\\Lecteur_Magic\\.openspec\\migration\\ADH\\ADH-IDE-119.analysis.json",
        "D:\\Projects\\Lecteur_Magic\\adh-web\\src\\types\\sessionList.ts",
        "D:\\Projects\\Lecteur_Magic\\adh-web\\src\\stores\\sessionListStore.ts",
        "D:\\Projects\\Lecteur_Magic\\adh-web\\src\\services\\api\\endpoints-sessionList.ts",
        "D:\\Projects\\Lecteur_Magic\\adh-web\\src\\pages\\SessionListPage.tsx",
        "D:\\Projects\\Lecteur_Magic\\adh-web\\src\\__tests__\\sessionListStore.test.ts",
        "D:\\Projects\\Lecteur_Magic\\adh-web\\src\\__tests__\\SessionListPage.test.tsx"
      ],
      "errors": [],
      "startedAt": "2026-02-22T21:31:33.098Z",
      "completedAt": "2026-02-22T21:31:33.179Z"
    },
    "121": {
      "status": "pending",
      "currentPhase": null,
      "phases": {},
      "files": [
        "D:\\Projects\\Lecteur_Magic\\.openspec\\specs\\ADH-IDE-121.md",
        "D:\\Projects\\Lecteur_Magic\\.openspec\\migration\\ADH\\ADH-IDE-121.contract.yaml",
        "D:\\Projects\\Lecteur_Magic\\.openspec\\migration\\ADH\\ADH-IDE-121.analysis.json",
        "D:\\Projects\\Lecteur_Magic\\adh-web\\src\\types\\gestionCaisse.ts",
        "D:\\Projects\\Lecteur_Magic\\adh-web\\src\\stores\\gestionCaisseStore.ts",
        "D:\\Projects\\Lecteur_Magic\\adh-web\\src\\services\\api\\endpoints-gestionCaisse.ts",
        "D:\\Projects\\Lecteur_Magic\\adh-web\\src\\pages\\GestionCaissePage.tsx",
        "D:\\Projects\\Lecteur_Magic\\adh-web\\src\\__tests__\\gestionCaisseStore.test.ts",
        "D:\\Projects\\Lecteur_Magic\\adh-web\\src\\__tests__\\GestionCaissePage.test.tsx"
      ],
      "errors": [],
      "startedAt": "2026-02-22T21:56:27.030Z",
      "completedAt": "2026-02-22T21:56:27.061Z"
    },
    "125": {
      "status": "pending",
      "currentPhase": null,
      "phases": {},
      "files": [
        "D:\\Projects\\Lecteur_Magic\\.openspec\\specs\\ADH-IDE-125.md",
        "D:\\Projects\\Lecteur_Magic\\.openspec\\migration\\ADH\\ADH-IDE-125.contract.yaml",
        "D:\\Projects\\Lecteur_Magic\\.openspec\\migration\\ADH\\ADH-IDE-125.analysis.json",
        "D:\\Projects\\Lecteur_Magic\\adh-web\\src\\types\\saisieContenuCaisse.ts",
        "D:\\Projects\\Lecteur_Magic\\adh-web\\src\\stores\\saisieContenuCaisseStore.ts",
        "D:\\Projects\\Lecteur_Magic\\adh-web\\src\\services\\api\\endpoints-saisieContenuCaisse.ts",
        "D:\\Projects\\Lecteur_Magic\\adh-web\\src\\pages\\SaisieContenuCaissePage.tsx",
        "D:\\Projects\\Lecteur_Magic\\adh-web\\src\\__tests__\\saisieContenuCaisseStore.test.ts",
        "D:\\Projects\\Lecteur_Magic\\adh-web\\src\\__tests__\\SaisieContenuCaissePage.test.tsx"
      ],
      "errors": [],
      "startedAt": "2026-02-22T21:19:37.816Z",
      "completedAt": "2026-02-22T21:19:37.885Z"
    },
    "131": {
      "status": "completed",
      "currentPhase": null,
      "phases": {
        "spec": {
          "status": "completed",
          "startedAt": "2026-02-23T16:26:22.631Z",
          "completedAt": "2026-02-23T16:26:22.645Z",
          "duration": 0,
          "file": "D:\\Projects\\Lecteur_Magic\\.openspec\\specs\\ADH-IDE-131.md"
        },
        "contract": {
          "status": "completed",
          "startedAt": "2026-02-23T16:26:22.646Z",
          "completedAt": "2026-02-23T16:26:22.646Z",
          "duration": 0,
          "file": "D:\\Projects\\Lecteur_Magic\\.openspec\\migration\\ADH\\ADH-IDE-131.contract.yaml"
        },
        "analyze": {
          "status": "completed",
          "startedAt": "2026-02-23T16:26:22.647Z",
          "completedAt": "2026-02-23T16:26:22.744Z",
          "duration": 0,
          "file": "D:\\Projects\\Lecteur_Magic\\.openspec\\migration\\ADH\\ADH-IDE-131.analysis.json"
        },
        "types": {
          "status": "completed",
          "startedAt": "2026-02-23T16:26:22.744Z",
          "completedAt": "2026-02-23T16:26:58.146Z",
          "duration": 35402,
          "file": "D:\\Projects\\Lecteur_Magic\\adh-web\\src\\types\\fermetureCaisse.ts"
        },
        "store": {
          "status": "completed",
          "startedAt": "2026-02-23T16:26:58.148Z",
          "completedAt": "2026-02-23T16:28:38.149Z",
          "duration": 100000,
          "file": "D:\\Projects\\Lecteur_Magic\\adh-web\\src\\stores\\fermetureCaisseStore.ts"
        },
        "api": {
          "status": "completed",
          "startedAt": "2026-02-23T16:28:38.150Z",
          "completedAt": "2026-02-23T16:29:03.309Z",
          "duration": 25159,
          "file": "D:\\Projects\\Lecteur_Magic\\adh-web\\src\\services\\api\\endpoints-fermetureCaisse.ts"
        },
        "page": {
          "status": "completed",
          "startedAt": "2026-02-23T16:29:03.311Z",
          "completedAt": "2026-02-23T16:30:24.625Z",
          "duration": 81314,
          "file": "D:\\Projects\\Lecteur_Magic\\adh-web\\src\\pages\\FermetureCaissePage.tsx"
        },
        "components": {
          "status": "completed",
          "startedAt": "2026-02-23T16:30:24.627Z",
          "completedAt": "2026-02-23T16:32:47.263Z",
          "duration": 142636
        },
        "tests-unit": {
          "status": "completed",
          "startedAt": "2026-02-23T16:32:47.264Z",
          "completedAt": "2026-02-23T16:34:27.929Z",
          "duration": 100665,
          "file": "D:\\Projects\\Lecteur_Magic\\adh-web\\src\\__tests__\\fermetureCaisseStore.test.ts"
        },
        "tests-ui": {
          "status": "completed",
          "startedAt": "2026-02-23T16:34:27.930Z",
          "completedAt": "2026-02-23T16:35:32.840Z",
          "duration": 64909,
          "file": "D:\\Projects\\Lecteur_Magic\\adh-web\\src\\__tests__\\FermetureCaissePage.test.tsx"
        }
      },
      "files": [
        "D:\\Projects\\Lecteur_Magic\\.openspec\\specs\\ADH-IDE-131.md",
        "D:\\Projects\\Lecteur_Magic\\.openspec\\migration\\ADH\\ADH-IDE-131.contract.yaml",
        "D:\\Projects\\Lecteur_Magic\\.openspec\\migration\\ADH\\ADH-IDE-131.analysis.json",
        "D:\\Projects\\Lecteur_Magic\\adh-web\\src\\types\\fermetureCaisse.ts",
        "D:\\Projects\\Lecteur_Magic\\adh-web\\src\\stores\\fermetureCaisseStore.ts",
        "D:\\Projects\\Lecteur_Magic\\adh-web\\src\\services\\api\\endpoints-fermetureCaisse.ts",
        "D:\\Projects\\Lecteur_Magic\\adh-web\\src\\pages\\FermetureCaissePage.tsx",
        "D:\\Projects\\Lecteur_Magic\\adh-web\\src\\__tests__\\fermetureCaisseStore.test.ts",
        "D:\\Projects\\Lecteur_Magic\\adh-web\\src\\__tests__\\FermetureCaissePage.test.tsx"
      ],
      "errors": [],
      "startedAt": "2026-02-22T20:41:25.796Z",
      "completedAt": "2026-02-23T16:35:32.840Z"
    },
    "132": {
      "status": "pending",
      "currentPhase": null,
      "phases": {},
      "files": [
        "D:\\Projects\\Lecteur_Magic\\.openspec\\specs\\ADH-IDE-132.md",
        "D:\\Projects\\Lecteur_Magic\\.openspec\\migration\\ADH\\ADH-IDE-132.contract.yaml",
        "D:\\Projects\\Lecteur_Magic\\.openspec\\migration\\ADH\\ADH-IDE-132.analysis.json",
        "D:\\Projects\\Lecteur_Magic\\adh-web\\src\\types\\sessionHistory.ts",
        "D:\\Projects\\Lecteur_Magic\\adh-web\\src\\stores\\sessionHistoryStore.ts",
        "D:\\Projects\\Lecteur_Magic\\adh-web\\src\\services\\api\\endpoints-sessionHistory.ts",
        "D:\\Projects\\Lecteur_Magic\\adh-web\\src\\pages\\SessionHistoryPage.tsx",
        "D:\\Projects\\Lecteur_Magic\\adh-web\\src\\__tests__\\sessionHistoryStore.test.ts",
        "D:\\Projects\\Lecteur_Magic\\adh-web\\src\\__tests__\\SessionHistoryPage.test.tsx"
      ],
      "errors": [],
      "startedAt": "2026-02-22T21:43:30.647Z",
      "completedAt": "2026-02-22T21:43:30.666Z"
    },
    "138": {
      "status": "pending",
      "currentPhase": null,
      "phases": {},
      "files": [
        "D:\\Projects\\Lecteur_Magic\\.openspec\\specs\\ADH-IDE-138.md",
        "D:\\Projects\\Lecteur_Magic\\.openspec\\migration\\ADH\\ADH-IDE-138.contract.yaml",
        "D:\\Projects\\Lecteur_Magic\\.openspec\\migration\\ADH\\ADH-IDE-138.analysis.json",
        "D:\\Projects\\Lecteur_Magic\\adh-web\\src\\types\\ticketFermetureSession.ts",
        "D:\\Projects\\Lecteur_Magic\\adh-web\\src\\stores\\ticketFermetureSessionStore.ts",
        "D:\\Projects\\Lecteur_Magic\\adh-web\\src\\services\\api\\endpoints-ticketFermetureSession.ts",
        "D:\\Projects\\Lecteur_Magic\\adh-web\\src\\pages\\TicketFermetureSessionPage.tsx",
        "D:\\Projects\\Lecteur_Magic\\adh-web\\src\\__tests__\\ticketFermetureSessionStore.test.ts",
        "D:\\Projects\\Lecteur_Magic\\adh-web\\src\\__tests__\\TicketFermetureSessionPage.test.tsx"
      ],
      "errors": [],
      "startedAt": "2026-02-22T21:19:37.947Z",
      "completedAt": "2026-02-22T21:19:37.956Z"
    },
    "155": {
      "status": "pending",
      "currentPhase": null,
      "phases": {},
      "files": [
        "D:\\Projects\\Lecteur_Magic\\.openspec\\specs\\ADH-IDE-155.md",
        "D:\\Projects\\Lecteur_Magic\\.openspec\\migration\\ADH\\ADH-IDE-155.contract.yaml",
        "D:\\Projects\\Lecteur_Magic\\.openspec\\migration\\ADH\\ADH-IDE-155.analysis.json",
        "D:\\Projects\\Lecteur_Magic\\adh-web\\src\\types\\controleFermetureCaisse.ts",
        "D:\\Projects\\Lecteur_Magic\\adh-web\\src\\stores\\controleFermetureCaisseStore.ts",
        "D:\\Projects\\Lecteur_Magic\\adh-web\\src\\services\\api\\endpoints-controleFermetureCaisse.ts",
        "D:\\Projects\\Lecteur_Magic\\adh-web\\src\\pages\\ControleFermetureCaissePage.tsx",
        "D:\\Projects\\Lecteur_Magic\\adh-web\\src\\__tests__\\controleFermetureCaisseStore.test.ts",
        "D:\\Projects\\Lecteur_Magic\\adh-web\\src\\__tests__\\ControleFermetureCaissePage.test.tsx"
      ],
      "errors": [],
      "startedAt": "2026-02-22T21:31:33.196Z",
      "completedAt": "2026-02-22T21:31:33.233Z"
    },
    "281": {
      "status": "pending",
      "currentPhase": null,
      "phases": {},
      "files": [
        "D:\\Projects\\Lecteur_Magic\\.openspec\\specs\\ADH-IDE-281.md",
        "D:\\Projects\\Lecteur_Magic\\.openspec\\migration\\ADH\\ADH-IDE-281.contract.yaml",
        "D:\\Projects\\Lecteur_Magic\\.openspec\\migration\\ADH\\ADH-IDE-281.analysis.json",
        "D:\\Projects\\Lecteur_Magic\\adh-web\\src\\types\\fermetureSessions.ts",
        "D:\\Projects\\Lecteur_Magic\\adh-web\\src\\stores\\fermetureSessionsStore.ts",
        "D:\\Projects\\Lecteur_Magic\\adh-web\\src\\services\\api\\endpoints-fermetureSessions.ts",
        "D:\\Projects\\Lecteur_Magic\\adh-web\\src\\pages\\FermetureSessionsPage.tsx",
        "D:\\Projects\\Lecteur_Magic\\adh-web\\src\\__tests__\\fermetureSessionsStore.test.ts",
        "D:\\Projects\\Lecteur_Magic\\adh-web\\src\\__tests__\\FermetureSessionsPage.test.tsx"
      ],
      "errors": [],
      "startedAt": "2026-02-22T22:09:14.066Z",
      "completedAt": "2026-02-22T22:09:14.087Z"
    }
  }
}